bricked/__init__.py
bricked/server/__init__.py
bricked/server/__main__.py
bricked/server/application.py
bricked/server/ioc_container.py
bricked/server/auth/__init__.py
bricked/server/auth/auth_routes.py
bricked/server/auth/constants.py
bricked/server/auth/controllers/__init__.py
bricked/server/auth/controllers/auth_controller.py
bricked/server/auth/controllers/login_controller.py
bricked/server/auth/controllers/registration_controller.py
bricked/server/auth/middleware/__init__.py
bricked/server/auth/middleware/auth_middleware.py
bricked/server/auth/middleware/exception.py
bricked/server/auth/services/__init__.py
bricked/server/auth/services/auth_service.py
bricked/server/controllers/__init__.py
bricked/server/controllers/controller.py
bricked/server/middleware/__init__.py
bricked/server/middleware/middleware.py
bricked/server/models/__init__.py
bricked/server/models/session_model.py
bricked/server/models/user_model.py
bricked/server/repositories/__init__.py
bricked/server/repositories/repository.py
bricked/server/repositories/session_repository.py
bricked/server/repositories/user_repository.py
bricked/server/routes/__init__.py
bricked/server/routes/router.py
bricked/server/routes/router_middleware.py
bricked/server/routes/routes.py
bricked/server/services/__init__.py
bricked/server/services/cookie_service.py
bricked/server/services/service.py
bricked/server/views/__init__.py
bricked_test/__init__.py
bricked_test/conftest.py
bricked_test/test_default_router.py
bricked-0.1.0.dist-info/METADATA
bricked-0.1.0.dist-info/WHEEL
bricked-0.1.0.dist-info/top_level.txt
bricked-0.1.0.dist-info/RECORD
